Metadata-Version: 1.1
Name: tensorbuilder
Version: 0.3.6
Summary: A light wrapper over TensorFlow that enables you to easily create complex deep neural networks using the Builder Pattern through a functional fluent immutable API
Home-page: https://github.com/cgarciae/tensorbuilder
Author: Cristian Garcia
Author-email: cgarcia.e88@gmail.com
License: MIT
Download-URL: https://github.com/cgarciae/tensorbuilder/tarball/0.3.6
Keywords: tensorflow,deep learning,neural networks
Platform: UNKNOWN
